src/__init__.py
src/cli.py
src/core.py
src/deploy/__init__.py
src/deploy/aliyun_oss.py
src/deploy/tencent_cos.py
tests/.gitignore
tests/test_cert_expired.py
tests/test_core.py
certship-0.1.13.dist-info/LICENSE
certship-0.1.13.dist-info/METADATA
certship-0.1.13.dist-info/WHEEL
certship-0.1.13.dist-info/entry_points.txt
certship-0.1.13.dist-info/RECORD
