Metadata-Version: 2.3
Name: certship
Version: 0.1.13
Summary: A tool for auto deploy cert to cloud storage service provider.
License: MIT
Author: laofahai
Author-email: laofahai@gmail.com
Requires-Python: >=3.7
Classifier: License :: OSI Approved :: MIT License
Classifier: Programming Language :: Python :: 3
Classifier: Programming Language :: Python :: 3.8
Classifier: Programming Language :: Python :: 3.9
Classifier: Programming Language :: Python :: 3.10
Classifier: Programming Language :: Python :: 3.11
Classifier: Programming Language :: Python :: 3.12
Classifier: Programming Language :: Python :: 3.13
Requires-Dist: cryptography
Requires-Dist: requests (>=2.32.4,<3.0.0)
